load_confounds/__init__.py
load_confounds/compcor.py
load_confounds/confounds.py
load_confounds/parser.py
load_confounds/strategies.py
load_confounds/data/__init__.py
load_confounds/data/invalid_desc-confounds_regressors.tsv
load_confounds/data/invalid_desc-confounds_timeseries.tsv
load_confounds/data/invalid_space-MNI152NLin2009cAsym_desc-preproc_bold.nii.gz
load_confounds/data/missing_desc-confounds_regressors.tsv
load_confounds/data/missing_space-MNI152NLin2009cAsym_desc-preproc_bold.nii.gz
load_confounds/data/noconfound_space-MNI152NLin2009cAsym_desc-preproc_bold.nii.gz
load_confounds/data/test_desc-confounds_regressors.tsv
load_confounds/data/test_space-MNI152NLin2009cAsym_desc-preproc_bold.nii.gz
load_confounds/data/test_space-MNI152NLin2009cAsym_desc-smoothAROMAnonaggr_bold.nii.gz
load_confounds/tests/__init__.py
load_confounds/tests/test_parser.py
load_confounds/tests/test_strategies.py
load_confounds-0.12.0.dist-info/LICENSE
load_confounds-0.12.0.dist-info/METADATA
load_confounds-0.12.0.dist-info/WHEEL
load_confounds-0.12.0.dist-info/top_level.txt
load_confounds-0.12.0.dist-info/RECORD
