Metadata-Version: 2.1
Name: load-confounds
Version: 0.12.0
Summary: load fMRIprep confounds in python
Home-page: https://github.com/simexp/load_confounds
Maintainer: Pierre Bellec
Maintainer-email: pierre.bellec@gmail.com
License: MIT
Project-URL: Bug Reports, https://github.com/simexp/load_confounds/issues
Project-URL: Funding, https://cneuromod.ca
Project-URL: Source, https://github.com/simexp/load_confounds
Platform: UNKNOWN
Classifier: Development Status :: 4 - Beta
Classifier: Intended Audience :: Developers
Classifier: Topic :: Software Development :: Build Tools
Classifier: License :: OSI Approved :: MIT License
Classifier: Programming Language :: Python :: 3.5
Classifier: Programming Language :: Python :: 3.6
Classifier: Programming Language :: Python :: 3.7
Classifier: Programming Language :: Python :: 3.8
Classifier: Programming Language :: Python :: 3.9
Requires-Python: >=3.5
License-File: LICENSE
Requires-Dist: numpy (>=1.17.4)
Requires-Dist: pandas (>=0.25.3)
Requires-Dist: scikit-learn (>=0.21.3)
Requires-Dist: scipy (>=1.3.2)
Requires-Dist: nilearn (>=0.7.1)
